README.rst
setup.py
src/rjs/__init__.py
src/rjs/base.py
src/rjs/tests.py
src/rjs.egg-info/PKG-INFO
src/rjs.egg-info/SOURCES.txt
src/rjs.egg-info/dependency_links.txt
src/rjs.egg-info/not-zip-safe
src/rjs.egg-info/top_level.txt