Metadata-Version: 1.1
Name: rjs
Version: 0.1.2
Summary: Redis json stroage.
Home-page: https://github.com/appstore-zencore/rjs
Author: zencore
Author-email: dobetter@zencore.cn
License: MIT
Keywords: rjs
Platform: UNKNOWN
Classifier: Development Status :: 5 - Production/Stable
Classifier: Intended Audience :: Developers
Classifier: Topic :: Software Development :: Libraries :: Python Modules
Classifier: License :: OSI Approved :: MIT License
Classifier: Programming Language :: Python :: 3
Classifier: Programming Language :: Python :: 3 :: Only
